h5cross/__init__.py
h5cross/checksamefiles.py
h5cross/cli.py
h5cross/hdfdict.py
h5cross/io.py
h5cross/nobvisual.py
h5cross/prettytable.py
h5cross/same_nob.py
h5cross/stats.py
h5cross/utils.py
h5cross/visit_h5.py
h5cross/convert/__init__.py
h5cross/convert/_convert.py
h5cross/convert/_nek5000.py
h5cross/convert/_utils.py
h5cross/convert/_vtk.py
h5cross/plotting/__init__.py
h5cross/plotting/_matplotlib.py
h5cross/plotting/_plotting.py
h5cross/plotting/_seaborn.py
h5cross/plotting/_utils.py
h5cross-0.2.7.dist-info/LICENSE
h5cross-0.2.7.dist-info/METADATA
h5cross-0.2.7.dist-info/WHEEL
h5cross-0.2.7.dist-info/entry_points.txt
h5cross-0.2.7.dist-info/top_level.txt
h5cross-0.2.7.dist-info/RECORD
