Metadata-Version: 2.1
Name: h5cross
Version: 0.2.7
Summary: Helper tools to handle H5 files
Home-page: https://gitlab.com/cerfacs/h5cross
Author: Jimmy-John Hoste, CoopTeam-CERFACS
Author-email: coop@cerfacs.fr
Project-URL: Homepage, https://gitlab.com/cerfacs/h5cross
Project-URL: Documentation, https://h5cross.readthedocs.io/en/latest/
Project-URL: Bug Tracker, https://gitlab.com/cerfacs/h5cross/-/issues
Keywords: hdf5,statistics,file conversion,visualization,scientific computing
Classifier: Programming Language :: Python :: 3.7
Classifier: Programming Language :: Python :: 3.8
Classifier: Programming Language :: Python :: 3.9
Classifier: Programming Language :: Python :: 3.10
Classifier: License :: OSI Approved :: MIT License
Requires-Python: >=3.7
License-File: LICENSE
Requires-Dist: click
Requires-Dist: pyyaml
Requires-Dist: h5py
Requires-Dist: numpy
Requires-Dist: pytest
Requires-Dist: prettytable
Provides-Extra: tests
Requires-Dist: pytest; extra == "tests"
Requires-Dist: pytest-coverage; extra == "tests"
Requires-Dist: prettytable; extra == "tests"
Requires-Dist: vtk; extra == "tests"
Requires-Dist: pymech; extra == "tests"
Requires-Dist: matplotlib; extra == "tests"
Requires-Dist: seaborn; extra == "tests"
Requires-Dist: scipy; extra == "tests"
Requires-Dist: nobvisual>=0.3; extra == "tests"
Requires-Dist: nob; extra == "tests"
Provides-Extra: vis
Requires-Dist: nob; extra == "vis"
Requires-Dist: scipy; extra == "vis"
Requires-Dist: matplotlib; extra == "vis"
